PyCROSL/AbsObjectiveFunc.py
PyCROSL/CRO_SL.py
PyCROSL/CompareTests.py
PyCROSL/CoralPopulation.py
PyCROSL/Substrate.py
PyCROSL/SubstrateInt.py
PyCROSL/SubstrateReal.py
PyCROSL/TestFunctions.py
PyCROSL/__init__.py
PyCROSL/evaluate_cro.py
PyCROSL/main.py
PyCROSL/operators.py
PyCROSL-1.1.dist-info/METADATA
PyCROSL-1.1.dist-info/WHEEL
PyCROSL-1.1.dist-info/top_level.txt
PyCROSL-1.1.dist-info/RECORD
