Metadata-Version: 2.1
Name: PyCROSL
Version: 1.1
Summary: Pyhton implementation of the "Coral Reef Optimization with Substrate Layers" algorithm
Home-page: https://github.com/jperezaracil/PyCROSL.git
Author: GHEODE
Author-email: 
License: MIT
